{
  "file_name": "088_网络安全原理与实践.md",
  "processed_at": "2025-11-08 18:48:55",
  "course_name": "网络安全原理与实践",
  "course_code": "B0501690",
  "course_goals": {
    "overview": "《网络安全原理与实践》是从事信息安全领域工作的入门课程，是计算机科学与技术专业的主要专业课，其目的是介绍网络安全基本理论与技术，包括网络攻击技术、网络安全编程、防火墙、恶意代码防护、VPN、无线网络安全技术以及网络安全协议等内容。通过本课程的学习，使学生初步掌握计算机网络安全的基本理论和基本方法，为进一步学习或从事信息安全领域的工作奠定必要的理论基础，结合国家网络安全战略和中华民族复兴的新时代背景，增强学生家国情怀与文化自信，激发学生使命感和责任心。",
    "goals": [
      {
        "number": "1",
        "content": "能够基于网络安全基本原理知识，了解发展趋势及其对社会发展的影响。能够运用网络安全基本原理和专业知识，分析处理网络系统运行过程中遇到的实际问题。"
      },
      {
        "number": "2",
        "content": "初步具备基本的网络安全功能原理、常用协议的分析能力；"
      },
      {
        "number": "3",
        "content": "初步具备在真实网络条件下，设计组建计算机网络安全防护系统的能力；具备开发简单的计算机网络安全系统的能力。"
      },
      {
        "number": "4",
        "content": "具有自主学习和终身学习意识及团队协作精神。"
      },
      {
        "number": "5",
        "content": "具备客观辩证、探索创新等基本科学素养，及时了解网络安全的国内外新技术和发展趋势，了解国家在相关方面的网络安全战略需求，树立强烈的爱国主义使命感与责任心。"
      }
    ]
  },
  "requirement_mappings": [
    {
      "table_title": "课程目标与计算机科学与技术专业毕业要求对应关系",
      "major": "计算机科学与技术",
      "mappings": [
        {
          "requirement_number": "1",
          "requirement": "工程知识：能够掌握数学、自然科学、计算机系统、物联网、计算机软件系统和计算机硬件体系知识，并应用在计算机相关领域的复杂工程问题的解决方案中。人工智能、大数据、网络安全等某个专业领域的知识，并用于解决计算机领域的复杂工程问题。",
          "indicator": "1-4",
          "course_goals": "目标1：0.4"
        },
        {
          "requirement_number": "3",
          "requirement": "设计/开发解决方案：能够设计计算机领域复杂工程问题的解决方案，设计与开发满足特定需求的软硬件系统、算法或部件，在设计中考虑社会、健康、安全、法律、文化以及环境等因素，并体现一定的创新意识。",
          "indicator": "3-4",
          "course_goals": "目标2 0.4"
        },
        {
          "requirement_number": "5",
          "requirement": "使用现代工具：能够针对复杂工程问题，开发、选择与使用恰当的技术、资源、现代工程工具和信息技术工具，包括对复杂工程问题的预测与模拟，并能够理解其局限性。",
          "indicator": "5-1",
          "course_goals": "目标2 0.5 目标3 0.5"
        },
        {
          "requirement_number": "6",
          "requirement": "工程与社会：能够基于计算机工程相关背景知识进行合理分析、认识和评价计算机工程实践和复杂工程问题解决方案对社会、健康、安全、法律以及文化的影响，并理解应承担的责任。",
          "indicator": "6-1",
          "course_goals": "目标1 0.4 目标2 0.4 目标5 0.2"
        },
        {
          "requirement_number": "7",
          "requirement": "环境和可持续发展：了解国家信息产业发展的宏观政策，能够理解和评价计算机复杂工程问题解决方案及专业工程实践对环境、社会可持续发展的影响。",
          "indicator": "7-2",
          "course_goals": "目标1 0.5 目标5 0.5"
        },
        {
          "requirement_number": "12",
          "requirement": "终身学习：具有自主学习和终身学习的意识，有不断学习和适应信息技术高速发展的能力。",
          "indicator": "12-1",
          "course_goals": "目标4 1.0"
        }
      ]
    },
    {
      "table_title": "表 **2.** 课程目标与智能财务（软件工程）专业毕业要求对应关系",
      "major": "智能财务（软件工程）",
      "mappings": [
        {
          "requirement_number": "1",
          "requirement": "毕业要求1：工程知识：能够掌握数学、自然科学、工程基础、计算机软件系统和计算机硬件体系知识，并应用在计算机相关领域的复杂工程问题的解决方案中。",
          "indicator": "1-4 掌握计算机系统、物联网、人工智能、大数据、网络安全等某个专业领域的知识，并用于解决计算机领域的复杂工程问题。",
          "course_goals": "目标1：0.4 目标2：0.4 目标3：0.2"
        },
        {
          "requirement_number": "3",
          "requirement": "毕业要求3：设计/开发解决方案：能够设计计算机领域复杂工程问题的解决方案，设计与开发满足特定需求的软硬件系统、算法或部件，在设计中考虑社会、健康、安全、法律、文化以及环境等因素，并体现一定的创新意识。",
          "indicator": "3-4 能够在设计环节中体现创新意识。",
          "course_goals": "目标3：1.0"
        },
        {
          "requirement_number": "5",
          "requirement": "毕业要求5：使用现代工具：能够针对复杂工程问题，开发、选择与使用恰当的技术、资源、现代工程工具和信息技术工具，包括对复杂工程问题的预测与模拟，并能够理解其局限性。",
          "indicator": "5-1：能够针对复杂工程问题，开发、选择与使用恰当的技术、资源、现代工程工具和信息技术工具",
          "course_goals": "目标2：0.5 目标3：0.5"
        },
        {
          "requirement_number": "6",
          "requirement": "毕业要求6：工程与社会 ：能够基于计算机工程相关背景知识进行合理分析 认识和评价计算机、工程实践和复杂工程问题解决方案对社会 健康 安全 法律以及文化的影响 并理解应承担的责任。",
          "indicator": "6 1能够基于计算机工程相关背景知识 合理分析与评价计算机工程实践和复杂工程问题解决方案对社会健康安全法律及文化的影响。",
          "course_goals": "目标1：0.4 目标2：0.4 目标5：0.2"
        },
        {
          "requirement_number": "7",
          "requirement": "毕业要求7：环境和可持续发展：了解国家信息产业发展的宏观政策，能够理解和评价计算机复杂工程问题解决方案及专业工程实践对环境、社会可持续发展的影响。",
          "indicator": "7-2能够在计算机复杂工程问题解决方案中，考虑与环境、社会的和谐可持续发展。",
          "course_goals": "目标1：0.5 目标5：0.5"
        },
        {
          "requirement_number": "12",
          "requirement": "毕业要求12：终身学习：具有自主学习和终身学习的意识，有不断学习和适应信息技术高速发展的能力。",
          "indicator": "12-1：具有自主学习和终身学习的意识。",
          "course_goals": "目标4：1.0"
        }
      ]
    }
  ],
  "course_relations": {
    "prerequisite_courses": [
      "计算机网络"
    ],
    "subsequent_courses": [],
    "description": ""
  }
}